gnwmanager/__init__.py
gnwmanager/__main__.py
gnwmanager/cli/__init__.py
gnwmanager/cli/_bootloader.py
gnwmanager/cli/_debug.py
gnwmanager/cli/_dump.py
gnwmanager/cli/_erase.py
gnwmanager/cli/_filesystem.py
gnwmanager/cli/_flash.py
gnwmanager/cli/_gdb.py
gnwmanager/cli/_install.py
gnwmanager/cli/_lock.py
gnwmanager/cli/_monitor.py
gnwmanager/cli/_parsers.py
gnwmanager/cli/_patch.py
gnwmanager/cli/_pull.py
gnwmanager/cli/_push.py
gnwmanager/cli/_screenshot.py
gnwmanager/cli/_sdcard.py
gnwmanager/cli/_start.py
gnwmanager/cli/_unlock.py
gnwmanager/cli/devices.py
gnwmanager/cli/gnw_patch/README.md
gnwmanager/cli/gnw_patch/__init__.py
gnwmanager/cli/gnw_patch/binaries/README.md
gnwmanager/cli/gnw_patch/binaries/__init__.py
gnwmanager/cli/gnw_patch/binaries/mario/0x08032000.bin
gnwmanager/cli/gnw_patch/binaries/mario/0x08032000.elf
gnwmanager/cli/gnw_patch/binaries/mario/__init__.py
gnwmanager/cli/gnw_patch/binaries/mario/default.bin
gnwmanager/cli/gnw_patch/binaries/mario/default.elf
gnwmanager/cli/gnw_patch/binaries/zelda/0x08032000.bin
gnwmanager/cli/gnw_patch/binaries/zelda/0x08032000.elf
gnwmanager/cli/gnw_patch/binaries/zelda/__init__.py
gnwmanager/cli/gnw_patch/binaries/zelda/default.bin
gnwmanager/cli/gnw_patch/binaries/zelda/default.elf
gnwmanager/cli/gnw_patch/compact_json_encoder.py
gnwmanager/cli/gnw_patch/compression.py
gnwmanager/cli/gnw_patch/exception.py
gnwmanager/cli/gnw_patch/firmware.py
gnwmanager/cli/gnw_patch/keystone_cache.json
gnwmanager/cli/gnw_patch/mario.py
gnwmanager/cli/gnw_patch/patch.py
gnwmanager/cli/gnw_patch/utils.py
gnwmanager/cli/gnw_patch/zelda.py
gnwmanager/cli/main.py
gnwmanager/elf.py
gnwmanager/exceptions.py
gnwmanager/filesystem.py
gnwmanager/firmware.bin
gnwmanager/gnw.py
gnwmanager/ocdbackend/__init__.py
gnwmanager/ocdbackend/base.py
gnwmanager/ocdbackend/openocd_backend.py
gnwmanager/ocdbackend/pyocd_backend.py
gnwmanager/py.typed
gnwmanager/status.py
gnwmanager/target.py
gnwmanager/time.py
gnwmanager/unlock.bin
gnwmanager-0.19.0.dist-info/LICENSE
gnwmanager-0.19.0.dist-info/METADATA
gnwmanager-0.19.0.dist-info/WHEEL
gnwmanager-0.19.0.dist-info/entry_points.txt
gnwmanager-0.19.0.dist-info/RECORD
