Metadata-Version: 2.3
Name: gnwmanager
Version: 0.19.0
Summary: 
License: Apache-2.0
Author: Brian Pugh
Requires-Python: >=3.9,<4.0
Classifier: License :: OSI Approved :: Apache Software License
Classifier: Programming Language :: Python :: 3
Classifier: Programming Language :: Python :: 3.9
Classifier: Programming Language :: Python :: 3.10
Classifier: Programming Language :: Python :: 3.11
Classifier: Programming Language :: Python :: 3.12
Classifier: Programming Language :: Python :: 3.13
Provides-Extra: pyocd
Requires-Dist: autoregistry (>=1.0.0,<2.0.0)
Requires-Dist: colorama (>=0.4.6,<0.5.0)
Requires-Dist: cyclopts (>=3.9.0,<4.0.0)
Requires-Dist: httpx (>=0.28.1,<0.29.0)
Requires-Dist: littlefs-python (>=0.9.0)
Requires-Dist: pillow (>=11.1.0,<12.0.0)
Requires-Dist: psutil (>=7.0.0,<8.0.0)
Requires-Dist: pycryptodome (>=3.21.0,<4.0.0)
Requires-Dist: pyelftools (>=0.29)
Requires-Dist: pyocd (>=0.35.1) ; extra == "pyocd"
Requires-Dist: rich (>=13.9.4,<14.0.0)
Requires-Dist: tamp (>=1.6.0,<2.0.0)
Requires-Dist: tqdm (>=4.66.6,<5.0.0)
Project-URL: Homepage, https://github.com/BrianPugh/gnwmanager
Project-URL: Repository, https://github.com/BrianPugh/gnwmanager
